{"url":"https://api.github.com/gists/57eef1739fb58834fa910145afff21ca/comments","status":200,"statusText":"OK","ok":true,"headers":{"date":["Sun, 14 May 2017 17:00:28 GMT"],"content-type":["application/json; charset=utf-8"],"transfer-encoding":["chunked"],"connection":["close"],"server":["GitHub.com"],"status":["200 OK"],"x-ratelimit-limit":["5000"],"x-ratelimit-remaining":["4908"],"x-ratelimit-reset":["1494783913"],"cache-control":["private, max-age=60, s-maxage=60"],"vary":["Accept, Authorization, Cookie, X-GitHub-OTP, Accept-Encoding, Accept-Encoding"],"etag":["W/\"448a2564f69635c00c4898e24e4f9d5d\""],"x-oauth-scopes":["gist, repo"],"x-accepted-oauth-scopes":[""],"x-github-media-type":["github.v3"],"access-control-expose-headers":["ETag, Link, X-GitHub-OTP, X-RateLimit-Limit, X-RateLimit-Remaining, X-RateLimit-Reset, X-OAuth-Scopes, X-Accepted-OAuth-Scopes, X-Poll-Interval"],"access-control-allow-origin":["*"],"content-security-policy":["default-src 'none'"],"strict-transport-security":["max-age=31536000; includeSubdomains; preload"],"x-content-type-options":["nosniff"],"x-frame-options":["deny"],"x-xss-protection":["1; mode=block"],"x-served-by":["62cdcc2d03a2f173f1c58590d1a90077"],"content-encoding":["gzip"],"x-github-request-id":["D96C:2AE86:B19219:DFFA02:59188D2C"]}}